argsy.py
argsy-1.0.3.dist-info/LICENSE
argsy-1.0.3.dist-info/METADATA
argsy-1.0.3.dist-info/WHEEL
argsy-1.0.3.dist-info/top_level.txt
argsy-1.0.3.dist-info/RECORD
