Metadata-Version: 2.1
Name: argsy
Version: 1.0.3
Summary: Tiny wrapper for Python's `argparse` package with YAML-based cli configuration.
Home-page: UNKNOWN
Author: Matt Wiley
License: UNKNOWN
Platform: UNKNOWN
License-File: LICENSE
Requires-Dist: PyYAML (>=5.4.1)
